pomisteremes/__init__.py
pomisteremes-1.0.dist-info/LICENSE
pomisteremes-1.0.dist-info/METADATA
pomisteremes-1.0.dist-info/WHEEL
pomisteremes-1.0.dist-info/top_level.txt
pomisteremes-1.0.dist-info/RECORD
